README.rst
bootstrap.py
buildout.cfg
setup.py
docs/HISTORY.rst
docs/INSTALL.rst
docs/LICENSE.GPL
docs/LICENSE.txt
quintagroup/__init__.py
quintagroup.silogroup.egg-info/PKG-INFO
quintagroup.silogroup.egg-info/SOURCES.txt
quintagroup.silogroup.egg-info/dependency_links.txt
quintagroup.silogroup.egg-info/entry_points.txt
quintagroup.silogroup.egg-info/namespace_packages.txt
quintagroup.silogroup.egg-info/not-zip-safe
quintagroup.silogroup.egg-info/requires.txt
quintagroup.silogroup.egg-info/top_level.txt
quintagroup/silogroup/__init__.py
quintagroup/silogroup/configure.zcml
quintagroup/silogroup/extender.py
quintagroup/silogroup/tests.py
quintagroup/silogroup/browser/__init__.py
quintagroup/silogroup/browser/configure.zcml
quintagroup/silogroup/browser/silo_navigation_form.pt
quintagroup/silogroup/browser/silonavigation.py
quintagroup/silogroup/interfaces/__init__.py
quintagroup/silogroup/interfaces/quintagroupsilogrouplayer.py
quintagroup/silogroup/portlets/__init__.py
quintagroup/silogroup/portlets/configure.zcml
quintagroup/silogroup/portlets/navigation.py
quintagroup/silogroup/portlets/navigation_recurse.pt
quintagroup/silogroup/profiles/default/actions.xml
quintagroup/silogroup/profiles/default/browserlayer.xml
quintagroup/silogroup/profiles/default/catalog.xml
quintagroup/silogroup/profiles/default/metadata.xml