Metadata-Version: 1.0
Name: quintagroup.silogroup
Version: 1.0
Summary: SiloGroup allows to generate custom navigation menu titles, hide or make them visible.
Home-page: https://github.com/quintagroup/quintagroup.silogroup
Author: Quintagroup
Author-email: support@quintagroup.com
License: GPL
Keywords: navigation title
Platform: UNKNOWN
Classifier: Framework :: Plone
Classifier: Programming Language :: Python
